deepl_scraper_pw/__init__.py
deepl_scraper_pw/deepl_tr.py
deepl_scraper_pw-0.1.0a0.dist-info/entry_points.txt
deepl_scraper_pw-0.1.0a0.dist-info/LICENSE
deepl_scraper_pw-0.1.0a0.dist-info/WHEEL
deepl_scraper_pw-0.1.0a0.dist-info/METADATA
deepl_scraper_pw-0.1.0a0.dist-info/RECORD
